mythica/__init__.py
mythica/catalog/__init__.py
mythica/catalog/abilities.py
mythica/catalog/creatures.py
mythica/catalog/effects.py
mythica/core/__init__.py
mythica/core/ability.py
mythica/core/creatures.py
mythica/core/ecosystem.py
mythica/core/context/__init__.py
mythica/core/context/context_ability.py
mythica/schema/__init__.py
mythica/schema/enums.py
mythica/utils/__init__.py
mythica/utils/ability_builder.py
mythica/utils/io_stream.py
mythica-1.0.0.dist-info/licenses/LICENSE
mythica-1.0.0.dist-info/METADATA
mythica-1.0.0.dist-info/WHEEL
mythica-1.0.0.dist-info/top_level.txt
mythica-1.0.0.dist-info/RECORD
