Metadata-Version: 2.4
Name: mythica
Version: 1.0.0
Summary: Lib for Simulation of fantasy ecosystems
Author-email: John Frederick Knight Berra / FrederickKnight <infisefir@gmail.com>
License: MIT License
Project-URL: Homepage, https://github.com/FrederickKnight/Mythica
Keywords: python,simulation,fantasy,creatures,abilities,ecosystems
Classifier: License :: OSI Approved :: MIT License
Classifier: Programming Language :: Python :: 3.12
Requires-Python: >=3.12
License-File: LICENSE
Requires-Dist: asteval>=1.0.6
Requires-Dist: numpy>=2.3.3
Requires-Dist: pydantic>=2.11.9
Requires-Dist: pyyaml>=6.0.2
Dynamic: license-file
